typed_lists-1.1.0.dist-info/METADATA
typed_lists-1.1.0.dist-info/WHEEL
typed_lists-1.1.0.dist-info/license_files/LICENSE
typed_lists/typed_list.py
typed_lists/_typed_lists_ext.pyi
typed_lists/__init__.py
typed_lists/_typed_lists_ext.cp310-win_amd64.pyd
typed_lists-1.1.0.dist-info/RECORD
